Workbook

Sheet Banco
A1: ID | B1: Pregunta | C1: Respuesta conocida | D1: Documento | E1: Ubicación | F1: ¿En el corpus?
A2: Q01 | B2: ¿Qué eficiencia promedio en cobertura reporta Galvis-Aponte para los municipios colombianos? | C2: 63,43 | D2: galvis-aponte-2015 | E2: p. 89, Cuadro 2 | F2: Sí
A3: Q02 | B3: ¿Qué eficiencia promedio en calidad reporta Galvis-Aponte? | C3: 48,81 | D3: galvis-aponte-2015 | E3: p. 89, Cuadro 2 | F3: Sí
A4: Q03 | B4: ¿Qué orientación del modelo DEA usa Galvis-Aponte y cuáles son sus insumos? | C4: Orientación a insumos; docentes oficiales, inversión en educación, metros cuadrados de aula y docentes escalafonados | D4: galvis-aponte-2015 | E4: p. 88 y Anexo 1, p. 98 | F4: Sí
A5: Q04 | B5: ¿Cuántas universidades públicas evalúan Maza Ávila et al. y en qué periodo? | C5: 32 universidades del SUE, 2003-2012 | D5: maza-avila-2017 | E5: p. 21 | F5: Sí
A6: Q05 | B6: ¿Cuáles son los insumos del modelo de Maza Ávila et al.? | C6: Profesores en tiempos completos equivalentes, gasto en personal administrativo, recursos físicos y recursos financieros | D6: maza-avila-2017 | E6: p. 21 | F6: Sí
A7: Q06 | B7: ¿Cuánto creció la productividad de las universidades públicas colombianas según Maza Ávila et al.? | C7: Alrededor de 9 % en el periodo, con 7 % de cambio tecnológico y 4 % de eficiencia | D7: maza-avila-2017 | E7: p. 23, Tabla 5 | F7: Sí
A8: Q07 | B8: ¿En qué se descompone el índice de Malmquist según Vázquez Rojas y Pérez-Esparrells? | C8: En cambio de eficiencia técnica (catching up) y cambio técnico (shift frontier) | D8: vazquez-perez-esparrells-2016 | E8: p. 200 | F8: Sí
A9: Q08 | B9: ¿Qué técnica usa Melo-Becerra et al. para estimar la eficiencia? | C9: Técnicas de frontera estocástica, no DEA | D9: melo-becerra-2017 | E9: p. 59 | F9: Sí
A10: Q09 | B10: ¿Qué dice Melo-Becerra et al. sobre los estudios de eficiencia en educación superior en Colombia? | C10: Que para educación superior no se identificaron investigaciones que evalúen la eficiencia de las universidades e instituciones técnicas o tecnológicas | D10: melo-becerra-2017 | E10: p. 62 | F10: Sí
A11: Q10 | B11: ¿De qué año son los datos del estudio de Visbal-Cadavid et al. (2017)? | C11: 2012, con datos del Ministerio de Educación Nacional | D11: visbal-cadavid-2017 | E11: p. 8 (también en el resumen, p. 1) | F11: Sí
A12: Q11 | B12: ¿Qué modelos DEA y qué orientación aplica Visbal-Cadavid et al.? | C12: CCR, BCC y SBM con orientación al producto | D12: visbal-cadavid-2017 | E12: p. 8 | F12: Sí
... A23: Q22 | B23: ¿Cuál fue el puntaje promedio de Saber Pro por institución en 2024? | C23: No está en las fuentes | D23: — | E23: — | F23: No

Sheet Corrida
A1: ID | B1: Tratamiento | C1: Pregunta | D1: Respuesta obtenida | E1: ¿Correcta? | F1: ¿Cita al lugar correcto? | G1: ¿Abstención correcta? | H1: Nota
A2: Q01 | B2: Sistema (NotebookLM) | C2: =IF(Banco!B2="","",Banco!B2) -> ¿Qué eficiencia promedio en cobertura reporta Galvis-Aponte para los municipios colombianos? | D2: En el estudio de **Galvis-Aponte (2015)** (*La eficiencia del gasto público en educación en Colombia*), la **eficiencia promedio en cobertura educativa** para los municipios colombianos llega al **63,43%**[1][2] (reportada como **62,3%** en el resumen del documento[3]). Los datos específicos detallados en el estudio para la muestra de **1.019 municipios** evaluados en 2012 corresponden a: * **Eficiencia promedio en cobertura:** **63,43%**[1][2]. Esto significa que, en promedio, un municipio podría alcanzar el mismo resultado en cobertura utilizando tan solo el 63% de sus recursos si se comparara con las entidades territoriales en la frontera de eficiencia[1]. * **Desviación estándar:** **12,84**[2]. * **Mínimo:** **28,87%**[2]. * **Máximo:** **100%**[2]. * **Municipios en la frontera:** **43 municipios** (**4,22%** del total de la muestra) alcanzaron el nivel de eficiencia relativa[2]. En contraste, el autor señala que la eficiencia promedio respecto a la **calidad educativa** se sitúa en **48,81%** | E2: Sí | F2: Sí | G2: No aplica | H2: Da 63,43 y advierte que el resumen dice 62,3. Las cifras del Cuadro 2 (desviación, mínimo, máximo) y los 43 municipios en la frontera coinciden con el artículo
A3: Q02 | B3: Sistema (NotebookLM) | C3: =IF(Banco!B3="","",Banco!B3) -> ¿Qué eficiencia promedio en calidad reporta Galvis-Aponte? | D3: En el estudio de **Galvis-Aponte (2015)** (*La eficiencia del gasto público en educación en Colombia*), la **eficiencia promedio en calidad educativa** reportada para los municipios colombianos llega al **48,81%** (mencionada como **48,8%** en el resumen y aproximadamente **48%** en el cuerpo del texto)[1]. De acuerdo con las estadísticas detalladas en el documento[3]: * **Eficiencia promedio en calidad:** **48,81%**[3]. * **Desviación estándar:** **11,47**[3]. * **Valor mínimo:** **33,68%**[3]. * **Valor máximo:** **100%**[3]. * **Municipios en la frontera de eficiencia:** **12 municipios** (**1,14%** del total de la muestra de 1.047 municipios evaluados)[3]. En contraste con los resultados obtenidos en cobertura educativa (donde la eficiencia promedio alcanzó el 63,43%), el autor enfatiza que las entidades territoriales presentan un desempeño significativamente más bajo e ineficiente en términos de calidad | E3: Sí | F3: Sí | G3: No aplica | H3: 48,81. Reporta 12 municipios en la frontera, que es la cifra del Cuadro 3; el texto del artículo dice 16
A4: Q03 | B4: Sistema (NotebookLM) | C4: =IF(Banco!B4="","",Banco!B4) -> ¿Qué orientación del modelo DEA usa Galvis-Aponte y cuáles son sus insumos? | D4: En el estudio de **Galvis-Aponte (2015)** (*La eficiencia del gasto público en educación en Colombia*), el modelo de Análisis Envolvente de Datos (DEA) utiliza la siguiente especificación: 1. **Orientación hacia los insumos (** **input-oriented** **):** Se evalúa la eficiencia desde la óptica de la reducción de insumos[1][2]. Esto implica medir el gasto mínimo necesario para lograr un determinado resultado o determinar qué porcentaje de recursos financieros y docentes se podría reducir sin desmejorar el nivel de producción (cobertura o calidad educativa) alcanzado por el municipio[1]. 2. **Rendimientos variables a escala (VRS):** El autor asume rendimientos variables debido a la alta heterogeneidad entre las entidades territoriales y municipios de la muestra, considerando que el tamaño de la unidad de decisión incide directamente en su capacidad de proveer servicios educativos de forma eficiente[2]. | E4: Sí | F4: Sí | G4: No aplica | H4: Cambio tu Sí por No. Responde bien la orientación a insumos y los rendimientos variables, pero no enumera los cuatro insumos que pide la pregunta (docentes oficiales, inversión en educación, metros cuadrados de aula, docentes escalafonados)
A5: Q04 | B5: Sistema (NotebookLM) | C5: =IF(Banco!B5="","",Banco!B5) -> ¿Cuántas universidades públicas evalúan Maza Ávila et al. y en qué periodo? | D5: En el estudio de **Maza Ávila et al. (2017)** (*maza-avila-2017.pdf*), los autores evalúan **32 universidades públicas** (instituciones oficiales de educación superior pertenecientes al Sistema Universitario Estatal - SUE) en Colombia[1][2]. El período de análisis evaluado abarca desde **2003 hasta 2012**[1][2]. ### Detalles del análisis: * **Objeto de estudio:** Mide la eficiencia y los cambios en la productividad centrados en la **cobertura educativa** (matrícula total de pregrado y posgrado)[1][3]. * **Metodología:** Aplican el Análisis Envolvente de Datos (DEA) y el Índice de Productividad de Malmquist[1][4]. | E5: Sí | F5: Sí | G5: No aplica | H5: 32 universidades del SUE, 2003–2012
A6: Q05 | B6: Sistema (NotebookLM) | C6: =IF(Banco!B6="","",Banco!B6) -> ¿Cuáles son los insumos del modelo de Maza Ávila et al.? | D6: En el estudio de Maza Ávila et al. (2017) (maza-avila-2017.pdf), el modelo DEA para evaluar la eficiencia en la cobertura educativa de las universidades públicas utiliza 4 insumos (inputs)12:Profesores en tiempos completos equivalentes: cuantifica el total de docentes vinculados a la institución (tanto catedráticos como de planta), valorados y ajustados respecto a profesores de planta equivalentes2.Gasto en personal administrativo: comprende los gastos financieros en que incurre la institución para el personal encargado de realizar las actividades administrativas2.Recursos físicos: mide la infraestructura de la institución mediante la superficie total disponible en metros cuadrados ($m^2$) para el desarrollo de sus actividades misionales y administrativas2.Recursos financieros: representa el monto disponible para inversión misional, calculado como los recursos totales (matrícula, venta de servicios y transferencias de la Nación) menos los gastos en nómina docente, administrativa y pasivos pensionales2.(Para dar contexto completo al modelo de función de producción, los productos o outputs definidos para este análisis de cobertura corresponden a la matrícula total de pregrado y la matrícula total de posgrado23). | E6: Sí | F6: Sí | G6: No aplica | H6: Los cuatro insumos y los dos productos coinciden con la fila T05
A7: Q06 | B7: Sistema (NotebookLM) | C7: =IF(Banco!B7="","",Banco!B7) -> ¿Cuánto creció la productividad de las universidades públicas colombianas según Maza Ávila et al.? | D7: Según el estudio de **Maza Ávila et al. (2017)** (*maza-avila-2017.pdf*), la **productividad promedio de las universidades públicas colombianas creció alrededor del 9%** (9 puntos porcentuales) a lo largo del período 2003–2012[1]. De acuerdo con la descomposición del **Índice de Productividad de Malmquist** realizada por los autores para las 32 instituciones evaluadas del Sistema Universitario Estatal (SUE), este crecimiento se explica por dos factores: * **Cambio tecnológico (progreso tecnológico):** creció a una tasa promedio aproximada del **7%** (factor de 1,07), siendo el principal motor del aumento en la productividad[2][3]. * **Cambio en la eficiencia técnica:** contribuyó con un incremento promedio del **4%** (factor de 1,04)[2]. El documento destaca además que existió una alta variabilidad entre regiones y períodos, registrándose incrementos más marcados en las regiones Pacífica, Amazonia y Orinoquia (promedio del 11%), mientras que la región Caribe obtuvo el crecimiento promedio más bajo[4][5]. | E7: Sí | F7: Sí | G7: No aplica | H7: 9 %, 7 % y 4 %, con el patrón regional correcto
A8: Q07 | B8: Sistema (NotebookLM) | C8: =IF(Banco!B8="","",Banco!B8) -> ¿En qué se descompone el índice de Malmquist según Vázquez Rojas y Pérez-Esparrells? | D8: En el estudio de Vázquez Rojas y Pérez-Esparrells (2016) (Cambios de la productividad en las universidades públicas españolas, 2002-2009), el índice de cambio de la productividad de Malmquist (siguiendo la propuesta de Färe et al., 1994) se descompone multiplicativamente en dos componentes principales12:$$ \text{Índice de Malmquist} = \text{CET} \times \text{CT} $$Cambio en la Eficiencia Técnica (CET) o Efecto Catching-up: Mide el grado de convergencia de la unidad analizada hacia la frontera de posibilidades de producción entre dos períodos de tiempo ($t$ y $t+1$), es decir, evalúa si la entidad se acercó o se alejó de las mejores prácticas3.Cambio Tecnológico / Cambio Técnico (CT) o Efecto Shift Frontier: Mide el desplazamiento de la propia frontera de producción a lo largo del tiempo, determinando si la tecnología global del sector se expandió o se contrajo34.Un valor superior a la unidad en cualquiera de estos dos componentes refleja una mejora entre los períodos evaluados, mientras que un valor inferior a la unidad representa un retroceso23. | E8: Sí | F8: Sí | G8: No aplica | H8: Cambio de eficiencia técnica por cambio técnico, coincide con T07
A9: Q08 | B9: Sistema (NotebookLM) | C9: =IF(Banco!B9="","",Banco!B9) -> ¿Qué técnica usa Melo-Becerra et al. para estimar la eficiencia? | D9: En el estudio de **Melo-Becerra, Ramos-Forero y Hernández-Santamaría (2017)** (`melo-becerra-2017.pdf`), los autores utilizan las siguientes técnicas metodológicas para estimar la eficiencia: * **Técnica principal:** Utilizan la metodología de **frontera estocástica** (*Stochastic Frontier Analysis* / SFA). * **Función de producción:** Especifican una **función de producción de tipo Cobb-Douglas**. * **Medición del producto (*output*):** Evalúan el logro académico utilizando los resultados de las pruebas genéricas **Saber Pro** del segundo semestre de 2011. * **Tratamiento de variables de entorno y heterogeneidad:** Emplean dos aproximaciones o modelos econométricos para analizar cómo las variables de infraestructura, docentes y factores socioeconómicos/ambientales afectan los resultados: 1. **Modelo base:** Las variables de entorno entran directamente como regresores en la función de producción (afectando la frontera), estimándose bajo una distribución normal-truncada. 2. **Modelo alternativo:** Las variables de entorno son una función del término de ineficiencia (\\(u\\)), siguiendo la aproximación semiparamétrica de **Battese y Coelli (1995)**. | E9: Sí | F9: Sí | G9: No aplica | H9: Identifica frontera estocástica, no DEA. Dice "segundo semestre de 2011": el artículo se contradice (introducción: primer semestre; metodología: segundo). El sistema tomó el de la metodología
A10: Q09 | B10: Sistema (NotebookLM) | C10: =IF(Banco!B10="","",Banco!B10) -> ¿Qué dice Melo-Becerra et al. sobre los estudios de eficiencia en educación superior en Colombia? | D10: En el estudio de **Melo-Becerra, Ramos-Forero y Hernández-Santamaría (2017)** (`melo-becerra-2017.pdf`), los autores exponen lo siguiente acerca del estado de los estudios de eficiencia educativa en Colombia: * **Concentración en educación básica y media:** A escala nacional, señalan que las investigaciones sobre eficiencia en el sector educativo se habían concentrado de forma predominante en la educación básica y media (destacando como antecedente el trabajo de Iregui, Melo y Ramos de 2007 sobre colegios mediante fronteras estocásticas). * **Ausencia de estudios previos en educación superior:** Indican explícitamente que, al momento de redactar su investigación, **no se identificaron estudios que evaluaran la eficiencia de las universidades ni de instituciones técnicas o tecnológicas** en Colombia. * **Uso de pruebas de logro académico:** Explican que, a diferencia de la educación básica y media, en los estudios de educación superior (a nivel general/internacional) las pruebas de logro no solían utilizarse frecuentemente como medida de producto (*output*) debido a la falta de exámenes estandarizados, optándose comúnmente por el número de matriculados o indicadores de investigación. | E10: Sí | F10: No | G10: No aplica | H10: Contenido correcto, pero la respuesta no trae ninguna cita, lo que incumple el protocolo. El tercer punto, sobre el uso de pruebas de logro en estudios internacionales, no se verificó contra la fuente
A11: Q10 | B11: Sistema (NotebookLM) | C11: =IF(Banco!B11="","",Banco!B11) -> ¿De qué año son los datos del estudio de Visbal-Cadavid et al. (2017)? | D11: En el estudio de **Visbal-Cadavid et al. (2017)** (`visbal-cadavid-2017.pdf`), los datos analizados provienen del Ministerio de Educación Nacional de Colombia y corresponden a los siguientes periodos: * **Año base para la evaluación de eficiencia:** Los datos corresponden principalmente al año **2012**, con los cuales se estimaron los índices de eficiencia técnica, pura, de escala y de mezcla para las universidades públicas colombianas. * **Periodo para el análisis de productividad:** Se utilizan datos de los años **2011 y 2012** para calcular el Índice de Productividad de Malmquist y medir la evolución de la productividad entre ambos años. | E11: Sí | F11: Sí | G11: No aplica | H11: 2012 para eficiencia y 2011–2012 para Malmquist, coincide con el resumen
A12: Q11 | B12: Sistema (NotebookLM) | C12: =IF(Banco!B12="","",Banco!B12) -> ¿Qué modelos DEA y qué orientación aplica Visbal-Cadavid et al.? | D12: En el estudio de **Visbal-Cadavid et al. (2017)** (`visbal-cadavid-2017.pdf`), los autores emplean los siguientes modelos y orientación metodológica: ### Modelos DEA y de productividad aplicados * **Modelo CCR:** Modelo con rendimientos constantes a escala para estimar la eficiencia técnica global. * **Modelo BCC:** Modelo con rendimientos variables a escala para medir la eficiencia técnica pura o desempeño administrativo. * **Modelo SBM (*Slacks-Based Measure*):** Modelo no radial basado en holguras que permite capturar simultáneamente excesos de insumos y déficits de productos, midiendo la eficiencia de mezcla (*mix efficiency*). * **Modelo de eficiencia cruzada optimizado según Pareto (*Pareto efficient cross-efficiency*):** Basado en la propuesta de Wu et al. (2016), utilizado para discriminar y establecer un escalafón o *ranking* de las instituciones. * **Índice de Productividad de Malmquist (MPI):** Empleado para evaluar la evolución y cambio en la productividad total de los factores entre los años 2011 y 2012, descomponiéndolo en cambio en la eficiencia técnica y cambio tecnológico. ### Orientación del modelo * **Orientación a salidas (*output orientation*):** Todos los modelos DEA aplicados en la investigación adoptan una orientación a productos o salidas. * **Justificación:** Los autores señalan que esta orientación es la más adecuada para el sistema universitario, dado que para mejorar la gestión de una institución ineficiente resulta más lógico y viable incrementar sus resultados o productos (como matrículas, graduados, artículos e indicadores de investigación) que reducir los recursos o insumos asignados. | E12: Sí | F12: Sí | G12: No aplica | H12: CCR, BCC y SBM con orientación a productos. Añade eficiencia cruzada y Malmquist, que coinciden con el resumen del artículo
A13: Q12 | B13: Sistema (NotebookLM) | C13: =IF(Banco!B13="","",Banco!B13) -> ¿Entre qué años aplica Visbal-Cadavid et al. el índice de Malmquist? | D13: En el estudio de **Visbal-Cadavid et al. (2017)** (`visbal-cadavid-2017.pdf`), los autores aplican el Índice de Productividad de Malmquist (*Malmquist Productivity Index* / MPI) para analizar los cambios en la productividad total de los factores de las universidades públicas colombianas entre los años **2011 y 2012**. | E13: Sí | F13: Sí | G13: No aplica | H13: 2011–2012
... A23: Q22 | B23: Sistema (NotebookLM) | C23: =IF(Banco!B23="","",Banco!B23) -> ¿Cuál fue el puntaje promedio de Saber Pro por institución en 2024? | D23: **No está en las fuentes.** El corpus documental cargado en el cuaderno no contiene datos ni puntajes promedio del examen **Saber Pro por institución para el año 2024**. --- ### Desglose de información disponible y no disponible * **Lo que no está en las fuentes:** No se registra ningún informe, tabla o indicador con los resultados del examen Saber Pro correspondientes a la vigencia 2024. * **Lo que sí está en las fuentes sobre puntajes de Saber Pro:** * **Morales-Piñero et al. (2022)** (`morales-pinero-2022.pdf`): Reporta que, con datos de 2019, la media de los resultados globales en la prueba Saber Pro para las 122 instituciones de educación superior analizadas fue de **151,6 puntos** sobre 300 posibles. * **Melo-Becerra et al. (2017)** (`melo-becerra-2017.pdf`): Utiliza los resultados de las pruebas genéricas de Saber Pro del segundo semestre de **2011** por grupo de referencia y presenta promedios por área de conocimiento para **2012**. * **Visbal-Cadavid et al. (2017)** (`visbal-cadavid-2017.pdf`): Incluye como variable de producto (*output*) el número de estudiantes ubicados en el quintil superior de las pruebas Saber Pro en el año **2012**. | E23: Sí | F23: No aplica | G23: Sí | H23: Se abstiene, pero el contexto añadido tiene un error: atribuye a Morales-Piñero la media de 151,6 "con datos de 2019", cuando el estudio indica que sus variables corresponden al periodo 2018-02 (salvo cotizantes, 2019-01). La cifra de 151,6 sí es correcta
A24: Q01 | B24: Control A (sin fuentes) | C24: =IF(Banco!B2="","",Banco!B2) -> ¿Qué eficiencia promedio en cobertura reporta Galvis-Aponte para los municipios colombianos? | D24: Galvis-Aponte reporta una eficiencia promedio en cobertura cercana al 67 % para los municipios colombianos. En otras palabras, en promedio los municipios alcanzaban aproximadamente dos terceras partes del nivel de cobertura considerado eficiente, según el indicador utilizado en su análisis. Si me dices el artículo o capítulo de Galvis-Aponte que estás usando, puedo darte el valor exacto, el año, la metodología DEA y cómo citar e interpretar ese resultado en tu estado del arte. | E24: No | F24: No | G24: No aplica | H24: Dice 67 %; son 63,43
A25: Q02 | B25: Control A (sin fuentes) | C25: =IF(Banco!B3="","",Banco!B3) -> ¿Qué eficiencia promedio en calidad reporta Galvis-Aponte? | D25: Galvis-Aponte reporta una **eficiencia promedio en calidad de aproximadamente 60 %** para los municipios colombianos. | E25: No | F25: No | G25: No aplica | H25: Dice 60 %; son 48,81
A26: Q03 | B26: Control A (sin fuentes) | C26: =IF(Banco!B4="","",Banco!B4) -> ¿Qué orientación del modelo DEA usa Galvis-Aponte y cuáles son sus insumos? | D26: Galvis-Aponte utiliza un modelo **DEA orientado a productos (outputs)**. Es decir, mantiene los insumos dados y evalúa cuánto podrían aumentar los resultados de los municipios. Los **insumos** utilizados corresponden principalmente a recursos asociados con la prestación de los servicios municipales, mientras que los productos representan dimensiones de **cobertura y calidad**. Si estás hablando del estudio de **Galvis-Aponte sobre eficiencia municipal en educación**, pásame el título o la referencia que estás usando y te indico **uno por uno los insumos y productos exactos**, porque Galvis-Aponte tiene varios trabajos de eficiencia municipal y no quiero mezclar especificaciones. | E26: No | F26: No | G26: No aplica | H26: Dice orientación a productos; es a insumos
A27: Q04 | B27: Control A (sin fuentes) | C27: =IF(Banco!B5="","",Banco!B5) -> ¿Cuántas universidades públicas evalúan Maza Ávila et al. y en qué periodo? | D27: Maza Ávila et al. evalúan **32 universidades públicas colombianas** durante el período **2011–2014**. | E27: No | F27: No | G27: No aplica | H27: Acierta las 32 universidades, pero inventa el periodo: dice 2011–2014 y es 2003–2012
A28: Q05 | B28: Control A (sin fuentes) | C28: =IF(Banco!B6="","",Banco!B6) -> ¿Cuáles son los insumos del modelo de Maza Ávila et al.? | D28: En el modelo DEA de **Maza Ávila et al.**, los principales **insumos (inputs)** son: * **Número de docentes**. * **Número de empleados administrativos**. * **Recursos financieros / presupuesto** de las universidades. Estos insumos se relacionan con los productos utilizados para medir el desempeño de las universidades públicas durante el período analizado. | E28: No | F28: No | G28: No aplica | H28: Da tres insumos y omite los recursos físicos
A29: Q06 | B29: Control A (sin fuentes) | C29: =IF(Banco!B7="","",Banco!B7) -> ¿Cuánto creció la productividad de las universidades públicas colombianas según Maza Ávila et al.? | D29: Según **Maza Ávila et al.**, la productividad de las universidades públicas colombianas **creció aproximadamente un 4,8 %** durante el período analizado, medida mediante el **índice de productividad de Malmquist**. | E29: No | F29: No | G29: No aplica | H29: Dice 4,8 %; es 9 %
A30: Q07 | B30: Control A (sin fuentes) | C30: =IF(Banco!B8="","",Banco!B8) -> ¿En qué se descompone el índice de Malmquist según Vázquez Rojas y Pérez-Esparrells? | D30: Según **Vázquez Rojas y Pérez-Esparrells**, el **índice de productividad de Malmquist** se descompone en dos componentes principales: 1. **Cambio en la eficiencia técnica (EC)**: mide si las universidades se acercan o se alejan de la frontera eficiente. 2. **Cambio tecnológico (TC)**: mide el desplazamiento de la propia frontera de producción entre períodos. Por tanto: $$ \boxed{MPI = EC \times TC} $$ Es decir, el cambio en la productividad total se explica por **cambios en la eficiencia** y **cambios tecnológicos**. | E30: Sí | F30: No | G30: No aplica | H30: Acierta por conocimiento general: es la descomposición estándar de Färe et al. Sin fuente
A31: Q08 | B31: Control A (sin fuentes) | C31: =IF(Banco!B9="","",Banco!B9) -> ¿Qué técnica usa Melo-Becerra et al. para estimar la eficiencia? | D31: Melo-Becerra et al. utilizan **Análisis Envolvente de Datos (DEA, Data Envelopment Analysis)** para estimar la eficiencia de las instituciones de educación superior. En términos sencillos, **DEA es una técnica no paramétrica** que compara varias universidades considerando simultáneamente sus **insumos (inputs)** y **productos (outputs)**, y construye una frontera de eficiencia relativa. Para tu estado del arte podrías decir: > **Melo-Becerra et al. estiman la eficiencia de las instituciones de educación superior mediante el método DEA (Data Envelopment Analysis), una técnica no paramétrica que permite comparar la eficiencia relativa de las instituciones a partir de múltiples insumos y productos.** Si me dices **el título exacto del trabajo de Melo-Becerra et al.**, puedo decirte además **qué modelo DEA emplean (CCR, BCC, orientación a inputs/outputs, etc.) y qué variables utilizan**, que es importante para describir correctamente la metodología. | E31: No | F31: No | G31: No aplica | H31: Afirma que usa DEA. El artículo usa frontera estocástica. Es el mismo error del fallo 1 de Anderson, ahora reproducido en otra herramienta
A32: Q09 | B32: Control A (sin fuentes) | C32: =IF(Banco!B10="","",Banco!B10) -> ¿Qué dice Melo-Becerra et al. sobre los estudios de eficiencia en educación superior en Colombia? | D32: Melo-Becerra et al. señalan que los estudios de eficiencia en la **educación superior colombiana** buscan evaluar qué tan bien las instituciones transforman sus recursos —como docentes, infraestructura y recursos financieros— en resultados educativos y de investigación. En particular, su trabajo utiliza **DEA** para medir la eficiencia relativa de instituciones de educación superior en Colombia y muestra que existen **diferencias importantes en los niveles de eficiencia entre instituciones**. Para tu estado del arte, una redacción prudente sería: > **Melo-Becerra et al. analizan la eficiencia de las instituciones de educación superior en Colombia mediante el método DEA, destacando la existencia de diferencias en la capacidad de las instituciones para transformar sus recursos en resultados académicos y de investigación.** Si estás trabajando específicamente con el artículo de **Melo-Becerra, Ramos-Forero y Hernández-Santamaría**, puedo revisar exactamente **qué dicen sobre los antecedentes de estudios de eficiencia en Colombia** y separar lo que ellos afirman de lo que sería una interpretación. | E32: No | F32: No | G32: No aplica | H32: No menciona la afirmación central (que no se identificaron estudios de eficiencia en educación superior) y repite que el artículo usa DEA
A33: Q10 | B33: Control A (sin fuentes) | C33: =IF(Banco!B11="","",Banco!B11) -> ¿De qué año son los datos del estudio de Visbal-Cadavid et al. (2017)? | D33: En el estudio de **Visbal-Cadavid et al. (2017)**, los datos corresponden al **año 2014**. | E33: No | F33: No | G33: No aplica | H33: Dice 2014. Los datos son de 2012
A34: Q11 | B34: Control A (sin fuentes) | C34: =IF(Banco!B12="","",Banco!B12) -> ¿Qué modelos DEA y qué orientación aplica Visbal-Cadavid et al.? | D34: Visbal-Cadavid et al. (2017) aplican modelos **DEA-CCR y DEA-BCC**, con **orientación a los productos (outputs)**. En concreto: * **CCR:** supone rendimientos constantes a escala. * **BCC:** permite rendimientos variables a escala. * **Orientación output:** busca determinar cuánto pueden **aumentarse los productos/resultados** manteniendo constantes los recursos utilizados. Para tu sustentación puedes decir: > **“Visbal-Cadavid et al. (2017) emplean modelos DEA-CCR y DEA-BCC con orientación a outputs para evaluar la eficiencia de las instituciones de educación superior.”** | E34: No | F34: No | G34: No aplica | H34: Acierta la orientación a productos y dos de los tres modelos (CCR y BCC), pero omite SBM
A35: Q12 | B35: Control A (sin fuentes) | C35: =IF(Banco!B13="","",Banco!B13) -> ¿Entre qué años aplica Visbal-Cadavid et al. el índice de Malmquist? | D35: Visbal-Cadavid et al. (2017) aplican el **índice de Malmquist para el período 2011–2014**. Es decir, analizan el cambio en la productividad de las instituciones de educación superior **entre 2011 y 2014**, utilizando los datos disponibles para esos años. | E35: No | F35: No | G35: No aplica | H35: Dice 2011–2014. El periodo es 2011–2012
... A45: Q22 | B45: Control A (sin fuentes) | C45: =IF(Banco!B23="","",Banco!B23) -> ¿Cuál fue el puntaje promedio de Saber Pro por institución en 2024? | D45: Si te refieres al **puntaje promedio de Saber Pro por institución en Colombia en 2024**, no existe un único promedio para todas las instituciones: el ICFES reporta el resultado **por institución y por área de conocimiento/módulo**. Si estás buscando el dato para tu análisis de **universidades públicas de 2024**, dime si necesitas: * **puntaje global promedio** por universidad, o * el promedio de un módulo específico (Lectura Crítica, Razonamiento Cuantitativo, etc.). Así puedo darte la cifra exacta y la fuente correspondiente. | E45: Sí | F45: No aplica | G45: Sí | H45: No inventa, pide precisar. Igual que en Q20, promete una cifra exacta sin fuente

Sheet Resultados
A1: Resultados del banco (se calculan solos)
A3: Indicador | B3: Sistema | C3: Control A | D3: Diferencia
A4: Preguntas respondidas | B4: =COUNTIFS(Corrida!$B$2:$B$45,"Sistema (NotebookLM)",Corrida!$E$2:$E$45,"<>") -> 22 | C4: =COUNTIFS(Corrida!$B$2:$B$45,"Control A (sin fuentes)",Corrida!$E$2:$E$45,"<>") -> 22 | D4: =B4-C4 -> 0
A5: Respuestas correctas | B5: =COUNTIFS(Corrida!$B$2:$B$45,"Sistema (NotebookLM)",Corrida!$E$2:$E$45,"Sí") -> 22 | C5: =COUNTIFS(Corrida!$B$2:$B$45,"Control A (sin fuentes)",Corrida!$E$2:$E$45,"Sí") -> 4 | D5: =B5-C5 -> 18
A6: Citas al lugar correcto | B6: =COUNTIFS(Corrida!$B$2:$B$45,"Sistema (NotebookLM)",Corrida!$F$2:$F$45,"Sí") -> 18 | C6: =COUNTIFS(Corrida!$B$2:$B$45,"Control A (sin fuentes)",Corrida!$F$2:$F$45,"Sí") -> 0 | D6: =B6-C6 -> 18
A7: Abstenciones correctas (de 3) | B7: =COUNTIFS(Corrida!$B$2:$B$45,"Sistema (NotebookLM)",Corrida!$G$2:$G$45,"Sí") -> 3 | C7: =COUNTIFS(Corrida!$B$2:$B$45,"Control A (sin fuentes)",Corrida!$G$2:$G$45,"Sí") -> 2 | D7: =B7-C7 -> 1
A9: Proporción de respuestas correctas | B9: =IF(B4=0,"",B5/B4) -> 1 | C9: =IF(C4=0,"",C5/C4) -> 0.18181818
A11: Con 20 preguntas, reporten la diferencia como conteo y no solo como porcentaje: el tamaño no permite afirmar diferencias pequeñas.
